{
  "sub_districts": [
    {
      "sub_district_id": 2001,
      "desa_kelurahan": "Alue Lhok"
    },
    {
      "sub_district_id": 2002,
      "desa_kelurahan": "Alue Bakong"
    },
    {
      "sub_district_id": 2003,
      "desa_kelurahan": "Berawang (Beurawang)"
    },
    {
      "sub_district_id": 2004,
      "desa_kelurahan": "Blang Sibeutong"
    },
    {
      "sub_district_id": 2005,
      "desa_kelurahan": "Cot Keumuneng"
    },
    {
      "sub_district_id": 2006,
      "desa_kelurahan": "Cot Lada"
    },
    {
      "sub_district_id": 2007,
      "desa_kelurahan": "Gunong Panah"
    },
    {
      "sub_district_id": 2008,
      "desa_kelurahan": "Kuta Padang"
    },
    {
      "sub_district_id": 2009,
      "desa_kelurahan": "Kuala Pling"
    },
    {
      "sub_district_id": 2010,
      "desa_kelurahan": "Layung"
    },
    {
      "sub_district_id": 2011,
      "desa_kelurahan": "Liceh"
    },
    {
      "sub_district_id": 2012,
      "desa_kelurahan": "Peulanteu SP (Peulanteu Sp)"
    },
    {
      "sub_district_id": 2013,
      "desa_kelurahan": "Rambong"
    },
    {
      "sub_district_id": 2014,
      "desa_kelurahan": "Seumuleng"
    },
    {
      "sub_district_id": 2015,
      "desa_kelurahan": "Suak Pangkat"
    },
    {
      "sub_district_id": 2016,
      "desa_kelurahan": "Seuneubok Trap"
    },
    {
      "sub_district_id": 2017,
      "desa_kelurahan": "Ulee Blang"
    }
  ]
}