{
  "sub_districts": [
    {
      "sub_district_id": 2001,
      "desa_kelurahan": "Talang Padang"
    },
    {
      "sub_district_id": 2002,
      "desa_kelurahan": "Tanjung Beringin"
    },
    {
      "sub_district_id": 2003,
      "desa_kelurahan": "Penantian"
    },
    {
      "sub_district_id": 2004,
      "desa_kelurahan": "Pagar Jati"
    },
    {
      "sub_district_id": 2005,
      "desa_kelurahan": "Kebon Jati (Keban Jati)"
    },
    {
      "sub_district_id": 2006,
      "desa_kelurahan": "Bandar Agung"
    },
    {
      "sub_district_id": 2007,
      "desa_kelurahan": "Lawang Agung"
    },
    {
      "sub_district_id": 2008,
      "desa_kelurahan": "Nanjungan"
    },
    {
      "sub_district_id": 2009,
      "desa_kelurahan": "Talang Randai"
    },
    {
      "sub_district_id": 2010,
      "desa_kelurahan": "Air Mayam (Air Mayan)"
    },
    {
      "sub_district_id": 2011,
      "desa_kelurahan": "Muara Rungga"
    },
    {
      "sub_district_id": 2012,
      "desa_kelurahan": "Padang Gelai"
    },
    {
      "sub_district_id": 2013,
      "desa_kelurahan": "Padang Bindu"
    },
    {
      "sub_district_id": 2014,
      "desa_kelurahan": "Muara Sindang"
    },
    {
      "sub_district_id": 2015,
      "desa_kelurahan": "Muara Aman"
    }
  ]
}