{
  "sub_districts": [
    {
      "sub_district_id": 2001,
      "desa_kelurahan": "Matandoi"
    },
    {
      "sub_district_id": 2002,
      "desa_kelurahan": "Dumagin A"
    },
    {
      "sub_district_id": 2003,
      "desa_kelurahan": "Dumagin B"
    },
    {
      "sub_district_id": 2004,
      "desa_kelurahan": "Dayow"
    },
    {
      "sub_district_id": 2005,
      "desa_kelurahan": "Onggunoi"
    },
    {
      "sub_district_id": 2006,
      "desa_kelurahan": "Modisi"
    },
    {
      "sub_district_id": 2007,
      "desa_kelurahan": "Posilagon"
    },
    {
      "sub_district_id": 2008,
      "desa_kelurahan": "Pidung"
    },
    {
      "sub_district_id": 2009,
      "desa_kelurahan": "Iligon"
    },
    {
      "sub_district_id": 2010,
      "desa_kelurahan": "Matandoi Selatan (Motandoi Selatan)"
    },
    {
      "sub_district_id": 2011,
      "desa_kelurahan": "Perjuangan"
    },
    {
      "sub_district_id": 2012,
      "desa_kelurahan": "Onggunoi Selatan"
    }
  ]
}