{
  "sub_districts": [
    {
      "sub_district_id": 1001,
      "desa_kelurahan": "Karang Tengah"
    },
    {
      "sub_district_id": 1002,
      "desa_kelurahan": "Karang Mulya"
    },
    {
      "sub_district_id": 1003,
      "desa_kelurahan": "Pondok Bahar"
    },
    {
      "sub_district_id": 1004,
      "desa_kelurahan": "Pondok Pucung"
    },
    {
      "sub_district_id": 1005,
      "desa_kelurahan": "Karang Timur"
    },
    {
      "sub_district_id": 1006,
      "desa_kelurahan": "Padurenan (Pedurenan)"
    },
    {
      "sub_district_id": 1007,
      "desa_kelurahan": "Parung Jaya"
    }
  ]
}