{
  "sub_districts": [
    {
      "sub_district_id": 2001,
      "desa_kelurahan": "Catubouw"
    },
    {
      "sub_district_id": 2002,
      "desa_kelurahan": "Bigwaimud"
    },
    {
      "sub_district_id": 2003,
      "desa_kelurahan": "Mihou"
    },
    {
      "sub_district_id": 2004,
      "desa_kelurahan": "Kaungwam"
    },
    {
      "sub_district_id": 2005,
      "desa_kelurahan": "Aiga"
    },
    {
      "sub_district_id": 2006,
      "desa_kelurahan": "Imandrigo"
    },
    {
      "sub_district_id": 2007,
      "desa_kelurahan": "Unti"
    },
    {
      "sub_district_id": 2008,
      "desa_kelurahan": "Ndabouw"
    },
    {
      "sub_district_id": 2009,
      "desa_kelurahan": "Sugemeh"
    },
    {
      "sub_district_id": 2010,
      "desa_kelurahan": "Manggesuk"
    },
    {
      "sub_district_id": 2011,
      "desa_kelurahan": "Ijigreg"
    },
    {
      "sub_district_id": 2012,
      "desa_kelurahan": "Jim"
    },
    {
      "sub_district_id": 2013,
      "desa_kelurahan": "Slomiou"
    },
    {
      "sub_district_id": 2014,
      "desa_kelurahan": "Binggrayud"
    },
    {
      "sub_district_id": 2015,
      "desa_kelurahan": "Minmo"
    },
    {
      "sub_district_id": 2016,
      "desa_kelurahan": "Mihij"
    },
    {
      "sub_district_id": 2017,
      "desa_kelurahan": "Soudin"
    },
    {
      "sub_district_id": 2018,
      "desa_kelurahan": "Timtouw"
    },
    {
      "sub_district_id": 2019,
      "desa_kelurahan": "Idemai"
    },
    {
      "sub_district_id": 2020,
      "desa_kelurahan": "Mieycomti"
    },
    {
      "sub_district_id": 2021,
      "desa_kelurahan": "Coijut"
    }
  ]
}