{
  "sub_districts": [
    {
      "sub_district_id": 2001,
      "desa_kelurahan": "Pepelegi"
    },
    {
      "sub_district_id": 2002,
      "desa_kelurahan": "Waru"
    },
    {
      "sub_district_id": 2003,
      "desa_kelurahan": "Kureksari"
    },
    {
      "sub_district_id": 2004,
      "desa_kelurahan": "Ngingas"
    },
    {
      "sub_district_id": 2005,
      "desa_kelurahan": "Tropodo"
    },
    {
      "sub_district_id": 2006,
      "desa_kelurahan": "Tambaksawah (Tambak Sawah)"
    },
    {
      "sub_district_id": 2007,
      "desa_kelurahan": "Tambakrejo (Tambak Rejo)"
    },
    {
      "sub_district_id": 2008,
      "desa_kelurahan": "Tambakoso (Tambak Oso)"
    },
    {
      "sub_district_id": 2009,
      "desa_kelurahan": "Tambaksumur (Tambak Sumur)"
    },
    {
      "sub_district_id": 2010,
      "desa_kelurahan": "Wadungasri"
    },
    {
      "sub_district_id": 2011,
      "desa_kelurahan": "Kepuhkiriman (Kepuh Kiriman)"
    },
    {
      "sub_district_id": 2012,
      "desa_kelurahan": "Berbek"
    },
    {
      "sub_district_id": 2013,
      "desa_kelurahan": "Wedoro"
    },
    {
      "sub_district_id": 2014,
      "desa_kelurahan": "Janti"
    },
    {
      "sub_district_id": 2015,
      "desa_kelurahan": "Kedungrejo"
    },
    {
      "sub_district_id": 2016,
      "desa_kelurahan": "Medaeng"
    },
    {
      "sub_district_id": 2017,
      "desa_kelurahan": "Bungurasih"
    }
  ]
}