{
  "sub_districts": [
    {
      "sub_district_id": 2001,
      "desa_kelurahan": "Sidangoli Gam"
    },
    {
      "sub_district_id": 2002,
      "desa_kelurahan": "Sidongoli Dehe (Sidangoli Dehe)"
    },
    {
      "sub_district_id": 2003,
      "desa_kelurahan": "Domato"
    },
    {
      "sub_district_id": 2004,
      "desa_kelurahan": "Tataleka"
    },
    {
      "sub_district_id": 2005,
      "desa_kelurahan": "Gamlenge"
    },
    {
      "sub_district_id": 2006,
      "desa_kelurahan": "Akejailolo (Ake Jailolo)"
    },
    {
      "sub_district_id": 2007,
      "desa_kelurahan": "Biamaahi"
    },
    {
      "sub_district_id": 2008,
      "desa_kelurahan": "Tuguraci"
    },
    {
      "sub_district_id": 2009,
      "desa_kelurahan": "Akeara"
    },
    {
      "sub_district_id": 2010,
      "desa_kelurahan": "Akelaha"
    },
    {
      "sub_district_id": 2011,
      "desa_kelurahan": "Dodinga"
    },
    {
      "sub_district_id": 2012,
      "desa_kelurahan": "Tewe"
    },
    {
      "sub_district_id": 2013,
      "desa_kelurahan": "Toniku"
    },
    {
      "sub_district_id": 2014,
      "desa_kelurahan": "Rioribati"
    },
    {
      "sub_district_id": 2021,
      "desa_kelurahan": "Taba Damai (DB)"
    },
    {
      "sub_district_id": 2022,
      "desa_kelurahan": "Moiso"
    },
    {
      "sub_district_id": 2023,
      "desa_kelurahan": "Braha"
    },
    {
      "sub_district_id": 2024,
      "desa_kelurahan": "Bangkit Rahmat"
    },
    {
      "sub_district_id": 2025,
      "desa_kelurahan": "Bobane Dano"
    },
    {
      "sub_district_id": 2026,
      "desa_kelurahan": "Suka Damai"
    },
    {
      "sub_district_id": 2027,
      "desa_kelurahan": "Hijrah"
    },
    {
      "sub_district_id": 2028,
      "desa_kelurahan": "Ratem"
    },
    {
      "sub_district_id": 2029,
      "desa_kelurahan": "Bobaneigo Madihutu"
    },
    {
      "sub_district_id": 2030,
      "desa_kelurahan": "Tetewang Joronga"
    },
    {
      "sub_district_id": 2031,
      "desa_kelurahan": "Akelamo Cinga-Cinga"
    },
    {
      "sub_district_id": 2032,
      "desa_kelurahan": "Akesahu Madutu"
    }
  ]
}