{
  "sub_districts": [
    {
      "sub_district_id": 2001,
      "desa_kelurahan": "Nanga Sebintang"
    },
    {
      "sub_district_id": 2002,
      "desa_kelurahan": "Nanga Lebangan"
    },
    {
      "sub_district_id": 2003,
      "desa_kelurahan": "Nanga Kalis"
    },
    {
      "sub_district_id": 2004,
      "desa_kelurahan": "Nanga Raun"
    },
    {
      "sub_district_id": 2005,
      "desa_kelurahan": "Bahenap"
    },
    {
      "sub_district_id": 2006,
      "desa_kelurahan": "Nanga Tubuk"
    },
    {
      "sub_district_id": 2007,
      "desa_kelurahan": "Nanga Danau"
    },
    {
      "sub_district_id": 2008,
      "desa_kelurahan": "Kensuray"
    },
    {
      "sub_district_id": 2009,
      "desa_kelurahan": "Rantau Kalis"
    },
    {
      "sub_district_id": 2010,
      "desa_kelurahan": "Kalis Raya"
    },
    {
      "sub_district_id": 2011,
      "desa_kelurahan": "Tekudak"
    },
    {
      "sub_district_id": 2012,
      "desa_kelurahan": "Semerantau"
    },
    {
      "sub_district_id": 2013,
      "desa_kelurahan": "Tapang Da'an (Tapang Daan)"
    },
    {
      "sub_district_id": 2014,
      "desa_kelurahan": "Segiam"
    },
    {
      "sub_district_id": 2016,
      "desa_kelurahan": "Ribang Kadeng"
    },
    {
      "sub_district_id": 2017,
      "desa_kelurahan": "Rantau Bumbun"
    },
    {
      "sub_district_id": 2018,
      "desa_kelurahan": "Peniung"
    }
  ]
}