{
  "sub_districts": [
    {
      "sub_district_id": 2001,
      "desa_kelurahan": "Kalinongko"
    },
    {
      "sub_district_id": 2002,
      "desa_kelurahan": "Trirejo"
    },
    {
      "sub_district_id": 2003,
      "desa_kelurahan": "Karangrejo"
    },
    {
      "sub_district_id": 2004,
      "desa_kelurahan": "Kalikalong"
    },
    {
      "sub_district_id": 2005,
      "desa_kelurahan": "Rimun"
    },
    {
      "sub_district_id": 2006,
      "desa_kelurahan": "Tepansari"
    },
    {
      "sub_district_id": 2007,
      "desa_kelurahan": "Kaliglagah (Kali Glagah)"
    },
    {
      "sub_district_id": 2008,
      "desa_kelurahan": "Tridadi"
    },
    {
      "sub_district_id": 2009,
      "desa_kelurahan": "Banyuasin Separe"
    },
    {
      "sub_district_id": 2010,
      "desa_kelurahan": "Guyangan"
    },
    {
      "sub_district_id": 2011,
      "desa_kelurahan": "Kalisemo"
    },
    {
      "sub_district_id": 2012,
      "desa_kelurahan": "Loano"
    },
    {
      "sub_district_id": 2013,
      "desa_kelurahan": "Jetis"
    },
    {
      "sub_district_id": 2014,
      "desa_kelurahan": "Kedungpoh"
    },
    {
      "sub_district_id": 2015,
      "desa_kelurahan": "Maron"
    },
    {
      "sub_district_id": 2016,
      "desa_kelurahan": "Kebongunung"
    },
    {
      "sub_district_id": 2017,
      "desa_kelurahan": "Mudalrejo"
    },
    {
      "sub_district_id": 2018,
      "desa_kelurahan": "Kemejing"
    },
    {
      "sub_district_id": 2019,
      "desa_kelurahan": "Banyuasin Kembaran"
    },
    {
      "sub_district_id": 2020,
      "desa_kelurahan": "Sedayu"
    },
    {
      "sub_district_id": 2021,
      "desa_kelurahan": "Ngargosari"
    }
  ]
}